azureml/__init__.py
azureml/tensorboard/__init__.py
azureml/tensorboard/export.py
azureml/tensorboard/tensorboard.py
azureml_tensorboard-1.60.0.dist-info/licenses/LICENSE.txt
azureml_tensorboard-1.60.0.dist-info/METADATA
azureml_tensorboard-1.60.0.dist-info/WHEEL
azureml_tensorboard-1.60.0.dist-info/top_level.txt
azureml_tensorboard-1.60.0.dist-info/RECORD
